streamlit_raw_echarts/__init__.py
streamlit_raw_echarts/example.py
streamlit_raw_echarts/frontend/index.html
streamlit_raw_echarts/frontend/data/city_coordinates.json
streamlit_raw_echarts/frontend/data/countries_regions_db.json
streamlit_raw_echarts/frontend/data/map_filename.json
streamlit_raw_echarts/frontend/js/ResizeSensor.js
streamlit_raw_echarts/frontend/js/bmap.min.js
streamlit_raw_echarts/frontend/js/bulma.min.css
streamlit_raw_echarts/frontend/js/echarts-gl.min.js
streamlit_raw_echarts/frontend/js/echarts-liquidfill.min.js
streamlit_raw_echarts/frontend/js/echarts-wordcloud.min.js
streamlit_raw_echarts/frontend/js/echarts.min.js
streamlit_raw_echarts/frontend/js/jquery-ui.css
streamlit_raw_echarts/frontend/js/jquery-ui.min.js
streamlit_raw_echarts/frontend/js/jquery.min.js
streamlit_raw_echarts/frontend/js/lodash.min.js
streamlit_raw_echarts/frontend/js/streamlit.component.js
streamlit_raw_echarts/frontend/js/utils.js
streamlit_raw_echarts/frontend/themes/chalk.js
streamlit_raw_echarts/frontend/themes/essos.js
streamlit_raw_echarts/frontend/themes/halloween.js
streamlit_raw_echarts/frontend/themes/index.js
streamlit_raw_echarts/frontend/themes/infographic.js
streamlit_raw_echarts/frontend/themes/macarons.js
streamlit_raw_echarts/frontend/themes/purple-passion.js
streamlit_raw_echarts/frontend/themes/roma.js
streamlit_raw_echarts/frontend/themes/romantic.js
streamlit_raw_echarts/frontend/themes/shine.js
streamlit_raw_echarts/frontend/themes/vintage.js
streamlit_raw_echarts/frontend/themes/walden.js
streamlit_raw_echarts/frontend/themes/westeros.js
streamlit_raw_echarts/frontend/themes/wonderland.js
streamlit_raw_echarts-0.1.4.dist-info/METADATA
streamlit_raw_echarts-0.1.4.dist-info/WHEEL
streamlit_raw_echarts-0.1.4.dist-info/top_level.txt
streamlit_raw_echarts-0.1.4.dist-info/RECORD
